{
	"cname":"用户登录页",
	"data": {
		"images":[
			"{{__STOR__::/__PROJECT_NAME/assets/user}}/images/signup_01.jpg",
			"{{__STOR__::/__PROJECT_NAME/assets/user}}/images/signup_02.jpg",
			"{{__STOR__::/__PROJECT_NAME/assets/user}}/images/signup_03.jpg",
			"{{__STOR__::/__PROJECT_NAME/assets/user}}/images/signup_04.jpg"
		],
		"option":{
			"api":"/xpmsns/user/user/option",
			"query":{}
		},
		"page":{
			"title":"用户登录"
		}
	},
	"entries":[
		{"method":"GET", "router":"/user/signin/mobile", "ttl":0}
	],
	"align": {
		"mobile":"/mobile/user/signin/mobile",
		"wechat":"/mobile/user/signin/wechat",
		"wxapp": "/user/signin"
	}
}